{"data": [{"attributes": {"address": "175 Thomas E Burgin Pkwy, Quincy, MA 02169", "at_street": null, "description": null, "latitude": 42.251809, "location_type": 1, "longitude": -71.005409, "municipality": "Quincy", "name": "Quincy Center", "on_street": null, "platform_code": null, "platform_name": null, "vehicle_type": null, "wheelchair_boarding": 1}, "id": "place-qnctr", "links": {"self": "/stops/place-qnctr"}, "relationships": {"facilities": {"links": {"related": "/facilities/?filter[stop]=place-qnctr"}}, "parent_station": {"data": null}, "zone": {"data": {"id": "CR-zone-1", "type": "zone"}}}, "type": "stop"}, {"attributes": {"address": null, "at_street": "Cottage Avenue", "description": null, "latitude": 42.247943, "location_type": 0, "longitude": -71.001554, "municipality": "Quincy", "name": "Hancock St opp Cottage Ave", "on_street": "Hancock Street", "platform_code": null, "platform_name": null, "vehicle_type": 3, "wheelchair_boarding": 1}, "id": "3326", "links": {"self": "/stops/3326"}, "relationships": {"facilities": {"links": {"related": "/facilities/?filter[stop]=3326"}}, "parent_station": {"data": null}, "zone": {"data": {"id": "LocalBus", "type": "zone"}}}, "type": "stop"}, {"attributes": {"address": null, "at_street": "Summer Street", "description": null, "latitude": 42.245267, "location_type": 0, "longitude": -71.000692, "municipality": "Quincy", "name": "School St @ Hancock St", "on_street": "School Street", "platform_code": null, "platform_name": null, "vehicle_type": 3, "wheelchair_boarding": 1}, "id": "3327", "links": {"self": "/stops/3327"}, "relationships": {"facilities": {"links": {"related": "/facilities/?filter[stop]=3327"}}, "parent_station": {"data": null}, "zone": {"data": {"id": "LocalBus", "type": "zone"}}}, "type": "stop"}, {"attributes": {"address": null, "at_street": "Gay Street", "description": null, "latitude": 42.244854, "location_type": 0, "longitude": -71.00151, "municipality": "Quincy", "name": "School St opp Gay St", "on_street": "School Street", "platform_code": null, "platform_name": null, "vehicle_type": 3, "wheelchair_boarding": 1}, "id": "3328", "links": {"self": "/stops/3328"}, "relationships": {"facilities": {"links": {"related": "/facilities/?filter[stop]=3328"}}, "parent_station": {"data": null}, "zone": {"data": {"id": "LocalBus", "type": "zone"}}}, "type": "stop"}, {"attributes": {"address": null, "at_street": "Water Street", "description": null, "latitude": 42.241968, "location_type": 0, "longitude": -71.003612, "municipality": "Quincy", "name": "Franklin St @ Water St", "on_street": "Franklin Street", "platform_code": null, "platform_name": null, "vehicle_type": 3, "wheelchair_boarding": 1}, "id": "3330", "links": {"self": "/stops/3330"}, "relationships": {"facilities": {"links": {"related": "/facilities/?filter[stop]=3330"}}, "parent_station": {"data": null}, "zone": {"data": {"id": "LocalBus", "type": "zone"}}}, "type": "stop"}, {"attributes": {"address": null, "at_street": "Pearl Street", "description": null, "latitude": 42.240881, "location_type": 0, "longitude": -71.003478, "municipality": "Quincy", "name": "Franklin St opp Pearl St", "on_street": "Franklin Street", "platform_code": null, "platform_name": null, "vehicle_type": 3, "wheelchair_boarding": 1}, "id": "3846", "links": {"self": "/stops/3846"}, "relationships": {"facilities": {"links": {"related": "/facilities/?filter[stop]=3846"}}, "parent_station": {"data": null}, "zone": {"data": {"id": "LocalBus", "type": "zone"}}}, "type": "stop"}, {"attributes": {"address": null, "at_street": "Bradford Street", "description": null, "latitude": 42.23883, "location_type": 0, "longitude": -71.003419, "municipality": "Quincy", "name": "Franklin St @ Presidents Ave", "on_street": "Franklin Street", "platform_code": null, "platform_name": null, "vehicle_type": 3, "wheelchair_boarding": 1}, "id": "3848", "links": {"self": "/stops/3848"}, "relationships": {"facilities": {"links": {"related": "/facilities/?filter[stop]=3848"}}, "parent_station": {"data": null}, "zone": {"data": {"id": "LocalBus", "type": "zone"}}}, "type": "stop"}, {"attributes": {"address": null, "at_street": "Goddard Street", "description": null, "latitude": 42.237968, "location_type": 0, "longitude": -71.003972, "municipality": "Quincy", "name": "Independence Ave @ Goddard St", "on_street": "Independence Avenue", "platform_code": null, "platform_name": null, "vehicle_type": 3, "wheelchair_boarding": 1}, "id": "3849", "links": {"self": "/stops/3849"}, "relationships": {"facilities": {"links": {"related": "/facilities/?filter[stop]=3849"}}, "parent_station": {"data": null}, "zone": {"data": {"id": "LocalBus", "type": "zone"}}}, "type": "stop"}, {"attributes": {"address": null, "at_street": "Parsons Street", "description": null, "latitude": 42.236417, "location_type": 0, "longitude": -71.004919, "municipality": "Quincy", "name": "Independence Ave @ Lawry St", "on_street": "Independence Avenue", "platform_code": null, "platform_name": null, "vehicle_type": 3, "wheelchair_boarding": 1}, "id": "3850", "links": {"self": "/stops/3850"}, "relationships": {"facilities": {"links": {"related": "/facilities/?filter[stop]=3850"}}, "parent_station": {"data": null}, "zone": {"data": {"id": "LocalBus", "type": "zone"}}}, "type": "stop"}, {"attributes": {"address": null, "at_street": "Federal Avenue", "description": null, "latitude": 42.235011, "location_type": 0, "longitude": -71.00578, "municipality": "Quincy", "name": "Independence Ave @ Federal Ave", "on_street": "Independence Avenue", "platform_code": null, "platform_name": null, "vehicle_type": 3, "wheelchair_boarding": 0}, "id": "3851", "links": {"self": "/stops/3851"}, "relationships": {"facilities": {"links": {"related": "/facilities/?filter[stop]=3851"}}, "parent_station": {"data": null}, "zone": {"data": {"id": "LocalBus", "type": "zone"}}}, "type": "stop"}, {"attributes": {"address": null, "at_street": "Verchild Street", "description": null, "latitude": 42.233513, "location_type": 0, "longitude": -71.006101, "municipality": "Quincy", "name": "Independence Ave opp Verchild St", "on_street": "Independence Avenue", "platform_code": null, "platform_name": null, "vehicle_type": 3, "wheelchair_boarding": 1}, "id": "3852", "links": {"self": "/stops/3852"}, "relationships": {"facilities": {"links": {"related": "/facilities/?filter[stop]=3852"}}, "parent_station": {"data": null}, "zone": {"data": {"id": "LocalBus", "type": "zone"}}}, "type": "stop"}, {"attributes": {"address": null, "at_street": "Lurton Street", "description": null, "latitude": 42.232065, "location_type": 0, "longitude": -71.005795, "municipality": "Quincy", "name": "Independence Ave opp Lurton St", "on_street": "Independence Avenue", "platform_code": null, "platform_name": null, "vehicle_type": 3, "wheelchair_boarding": 1}, "id": "3853", "links": {"self": "/stops/3853"}, "relationships": {"facilities": {"links": {"related": "/facilities/?filter[stop]=3853"}}, "parent_station": {"data": null}, "zone": {"data": {"id": "LocalBus", "type": "zone"}}}, "type": "stop"}, {"attributes": {"address": null, "at_street": "Holmes Street", "description": null, "latitude": 42.229833, "location_type": 0, "longitude": -71.005345, "municipality": "Braintree", "name": "41 Independence Ave", "on_street": "Independence Avenue", "platform_code": null, "platform_name": null, "vehicle_type": 3, "wheelchair_boarding": 1}, "id": "3854", "links": {"self": "/stops/3854"}, "relationships": {"facilities": {"links": {"related": "/facilities/?filter[stop]=3854"}}, "parent_station": {"data": null}, "zone": {"data": {"id": "LocalBus", "type": "zone"}}}, "type": "stop"}, {"attributes": {"address": null, "at_street": "Centre Street", "description": null, "latitude": 42.228247, "location_type": 0, "longitude": -71.004983, "municipality": "Braintree", "name": "Independence Ave @ Centre St", "on_street": "Independence Avenue", "platform_code": null, "platform_name": null, "vehicle_type": 3, "wheelchair_boarding": 0}, "id": "3855", "links": {"self": "/stops/3855"}, "relationships": {"facilities": {"links": {"related": "/facilities/?filter[stop]=3855"}}, "parent_station": {"data": null}, "zone": {"data": {"id": "LocalBus", "type": "zone"}}}, "type": "stop"}, {"attributes": {"address": "Burgin Pkwy and Centre St, Quincy, MA 02169", "at_street": null, "description": null, "latitude": 42.233391, "location_type": 1, "longitude": -71.007153, "municipality": "Quincy", "name": "Quincy Adams", "on_street": null, "platform_code": null, "platform_name": null, "vehicle_type": null, "wheelchair_boarding": 1}, "id": "place-qamnl", "links": {"self": "/stops/place-qamnl"}, "relationships": {"facilities": {"links": {"related": "/facilities/?filter[stop]=place-qamnl"}}, "parent_station": {"data": null}, "zone": {"data": null}}, "type": "stop"}, {"attributes": {"address": null, "at_street": "Liberty Street", "description": null, "latitude": 42.234648, "location_type": 0, "longitude": -71.011635, "municipality": "Quincy", "name": "Centre St @ Liberty St", "on_street": "Centre Street", "platform_code": null, "platform_name": null, "vehicle_type": 3, "wheelchair_boarding": 1}, "id": "41035", "links": {"self": "/stops/41035"}, "relationships": {"facilities": {"links": {"related": "/facilities/?filter[stop]=41035"}}, "parent_station": {"data": null}, "zone": {"data": {"id": "LocalBus", "type": "zone"}}}, "type": "stop"}, {"attributes": {"address": null, "at_street": "Intervale Street", "description": null, "latitude": 42.236354, "location_type": 0, "longitude": -71.013361, "municipality": "Quincy", "name": "Centre St @ Intervale St", "on_street": "Centre Street", "platform_code": null, "platform_name": null, "vehicle_type": 3, "wheelchair_boarding": 1}, "id": "1633", "links": {"self": "/stops/1633"}, "relationships": {"facilities": {"links": {"related": "/facilities/?filter[stop]=1633"}}, "parent_station": {"data": null}, "zone": {"data": {"id": "LocalBus", "type": "zone"}}}, "type": "stop"}, {"attributes": {"address": null, "at_street": "Brooks Avenue", "description": null, "latitude": 42.238052, "location_type": 0, "longitude": -71.015087, "municipality": "Quincy", "name": "Centre St @ Brooks Ave", "on_street": "Centre Street", "platform_code": null, "platform_name": null, "vehicle_type": 3, "wheelchair_boarding": 1}, "id": "1634", "links": {"self": "/stops/1634"}, "relationships": {"facilities": {"links": {"related": "/facilities/?filter[stop]=1634"}}, "parent_station": {"data": null}, "zone": {"data": {"id": "LocalBus", "type": "zone"}}}, "type": "stop"}, {"attributes": {"address": null, "at_street": "Granite Street", "description": null, "latitude": 42.239724, "location_type": 0, "longitude": -71.016759, "municipality": "Quincy", "name": "Centre St @ Granite St", "on_street": "Centre Street", "platform_code": null, "platform_name": null, "vehicle_type": 3, "wheelchair_boarding": 1}, "id": "1635", "links": {"self": "/stops/1635"}, "relationships": {"facilities": {"links": {"related": "/facilities/?filter[stop]=1635"}}, "parent_station": {"data": null}, "zone": {"data": {"id": "LocalBus", "type": "zone"}}}, "type": "stop"}, {"attributes": {"address": null, "at_street": "McDonald Street", "description": null, "latitude": 42.241264, "location_type": 0, "longitude": -71.019356, "municipality": "Quincy", "name": "Centre St @ Kent St", "on_street": "Centre Street", "platform_code": null, "platform_name": null, "vehicle_type": 3, "wheelchair_boarding": 1}, "id": "1636", "links": {"self": "/stops/1636"}, "relationships": {"facilities": {"links": {"related": "/facilities/?filter[stop]=1636"}}, "parent_station": {"data": null}, "zone": {"data": {"id": "LocalBus", "type": "zone"}}}, "type": "stop"}, {"attributes": {"address": null, "at_street": "Centre Street", "description": null, "latitude": 42.241968, "location_type": 0, "longitude": -71.021578, "municipality": "Quincy", "name": "West St @ Centre St", "on_street": "West Street", "platform_code": null, "platform_name": null, "vehicle_type": 3, "wheelchair_boarding": 1}, "id": "1637", "links": {"self": "/stops/1637"}, "relationships": {"facilities": {"links": {"related": "/facilities/?filter[stop]=1637"}}, "parent_station": {"data": null}, "zone": {"data": {"id": "LocalBus", "type": "zone"}}}, "type": "stop"}, {"attributes": {"address": null, "at_street": "Hynes Avenue", "description": null, "latitude": 42.24158, "location_type": 0, "longitude": -71.022923, "municipality": "Quincy", "name": "West St @ Lyons St", "on_street": "West Street", "platform_code": null, "platform_name": null, "vehicle_type": 3, "wheelchair_boarding": 1}, "id": "1638", "links": {"self": "/stops/1638"}, "relationships": {"facilities": {"links": {"related": "/facilities/?filter[stop]=1638"}}, "parent_station": {"data": null}, "zone": {"data": {"id": "LocalBus", "type": "zone"}}}, "type": "stop"}, {"attributes": {"address": null, "at_street": "Sullivan Road", "description": null, "latitude": 42.240748, "location_type": 0, "longitude": -71.024085, "municipality": "Quincy", "name": "West St @ Ida St", "on_street": "West Street", "platform_code": null, "platform_name": null, "vehicle_type": 3, "wheelchair_boarding": 1}, "id": "1639", "links": {"self": "/stops/1639"}, "relationships": {"facilities": {"links": {"related": "/facilities/?filter[stop]=1639"}}, "parent_station": {"data": null}, "zone": {"data": {"id": "LocalBus", "type": "zone"}}}, "type": "stop"}, {"attributes": {"address": null, "at_street": "Doble Street", "description": null, "latitude": 42.239285, "location_type": 0, "longitude": -71.025263, "municipality": "Quincy", "name": "West St @ Doble St", "on_street": "West Street", "platform_code": null, "platform_name": null, "vehicle_type": 3, "wheelchair_boarding": 1}, "id": "1640", "links": {"self": "/stops/1640"}, "relationships": {"facilities": {"links": {"related": "/facilities/?filter[stop]=1640"}}, "parent_station": {"data": null}, "zone": {"data": {"id": "LocalBus", "type": "zone"}}}, "type": "stop"}, {"attributes": {"address": null, "at_street": "Hayden Street", "description": null, "latitude": 42.238421, "location_type": 0, "longitude": -71.025546, "municipality": "Quincy", "name": "West St @ Hayden St", "on_street": "West Street", "platform_code": null, "platform_name": null, "vehicle_type": 3, "wheelchair_boarding": 1}, "id": "1641", "links": {"self": "/stops/1641"}, "relationships": {"facilities": {"links": {"related": "/facilities/?filter[stop]=1641"}}, "parent_station": {"data": null}, "zone": {"data": {"id": "LocalBus", "type": "zone"}}}, "type": "stop"}, {"attributes": {"address": null, "at_street": "Wickford Lane", "description": null, "latitude": 42.237318, "location_type": 0, "longitude": -71.026229, "municipality": "Quincy", "name": "West St @ Wickford Ln", "on_street": "West Street", "platform_code": null, "platform_name": null, "vehicle_type": 3, "wheelchair_boarding": 1}, "id": "1642", "links": {"self": "/stops/1642"}, "relationships": {"facilities": {"links": {"related": "/facilities/?filter[stop]=1642"}}, "parent_station": {"data": null}, "zone": {"data": {"id": "LocalBus", "type": "zone"}}}, "type": "stop"}, {"attributes": {"address": null, "at_street": "Wesson Avenue", "description": null, "latitude": 42.235942, "location_type": 0, "longitude": -71.028228, "municipality": "Quincy", "name": "West St @ Willard St", "on_street": "West Street", "platform_code": null, "platform_name": null, "vehicle_type": 3, "wheelchair_boarding": 1}, "id": "1643", "links": {"self": "/stops/1643"}, "relationships": {"facilities": {"links": {"related": "/facilities/?filter[stop]=1643"}}, "parent_station": {"data": null}, "zone": {"data": {"id": "LocalBus", "type": "zone"}}}, "type": "stop"}, {"attributes": {"address": null, "at_street": "Ames Street", "description": null, "latitude": 42.234801, "location_type": 0, "longitude": -71.028609, "municipality": "Quincy", "name": "Willard St opp Ames St", "on_street": "Willard Street", "platform_code": null, "platform_name": null, "vehicle_type": 3, "wheelchair_boarding": 1}, "id": "1644", "links": {"self": "/stops/1644"}, "relationships": {"facilities": {"links": {"related": "/facilities/?filter[stop]=1644"}}, "parent_station": {"data": null}, "zone": {"data": {"id": "LocalBus", "type": "zone"}}}, "type": "stop"}, {"attributes": {"address": null, "at_street": "Purgatory Road", "description": null, "latitude": 42.2295, "location_type": 0, "longitude": -71.03111, "municipality": "Quincy", "name": "Willard St opp Thistle Rd", "on_street": "Willard Street", "platform_code": null, "platform_name": null, "vehicle_type": 3, "wheelchair_boarding": 1}, "id": "1647", "links": {"self": "/stops/1647"}, "relationships": {"facilities": {"links": {"related": "/facilities/?filter[stop]=1647"}}, "parent_station": {"data": null}, "zone": {"data": {"id": "LocalBus", "type": "zone"}}}, "type": "stop"}, {"attributes": {"address": null, "at_street": null, "description": null, "latitude": 42.22775, "location_type": 0, "longitude": -71.031639, "municipality": "Braintree", "name": "859 Willard St", "on_street": "Granite Street", "platform_code": null, "platform_name": null, "vehicle_type": 3, "wheelchair_boarding": 1}, "id": "1648", "links": {"self": "/stops/1648"}, "relationships": {"facilities": {"links": {"related": "/facilities/?filter[stop]=1648"}}, "parent_station": {"data": null}, "zone": {"data": {"id": "LocalBus", "type": "zone"}}}, "type": "stop"}, {"attributes": {"address": null, "at_street": "Wood Road", "description": null, "latitude": 42.225872, "location_type": 0, "longitude": -71.032036, "municipality": "Braintree", "name": "Granite St @ Wood Rd", "on_street": "Granite Street", "platform_code": null, "platform_name": null, "vehicle_type": 3, "wheelchair_boarding": 1}, "id": "1649", "links": {"self": "/stops/1649"}, "relationships": {"facilities": {"links": {"related": "/facilities/?filter[stop]=1649"}}, "parent_station": {"data": null}, "zone": {"data": {"id": "LocalBus", "type": "zone"}}}, "type": "stop"}, {"attributes": {"address": null, "at_street": null, "description": null, "latitude": 42.219946, "location_type": 0, "longitude": -71.027761, "municipality": "Braintree", "name": "Granite St @ Partridge Hill Rd", "on_street": "Granite Street", "platform_code": null, "platform_name": null, "vehicle_type": 3, "wheelchair_boarding": 1}, "id": "1650", "links": {"self": "/stops/1650"}, "relationships": {"facilities": {"links": {"related": "/facilities/?filter[stop]=1650"}}, "parent_station": {"data": null}, "zone": {"data": {"id": "LocalBus", "type": "zone"}}}, "type": "stop"}, {"attributes": {"address": null, "at_street": "Davis Road", "description": null, "latitude": 42.215992, "location_type": 0, "longitude": -71.023141, "municipality": "Braintree", "name": "Granite St @ Davis Rd", "on_street": "Granite Street", "platform_code": null, "platform_name": null, "vehicle_type": 3, "wheelchair_boarding": 1}, "id": "4023", "links": {"self": "/stops/4023"}, "relationships": {"facilities": {"links": {"related": "/facilities/?filter[stop]=4023"}}, "parent_station": {"data": null}, "zone": {"data": {"id": "LocalBus", "type": "zone"}}}, "type": "stop"}, {"attributes": {"address": "Union St and Center St, Randolph, MA 02368", "at_street": null, "description": null, "latitude": 42.156343, "location_type": 1, "longitude": -71.027371, "municipality": "Randolph", "name": "Holbrook/Randolph", "on_street": null, "platform_code": null, "platform_name": null, "vehicle_type": null, "wheelchair_boarding": 1}, "id": "place-MM-0150", "links": {"self": "/stops/place-MM-0150"}, "relationships": {"facilities": {"links": {"related": "/facilities/?filter[stop]=place-MM-0150"}}, "parent_station": {"data": null}, "zone": {"data": {"id": "CR-zone-3", "type": "zone"}}}, "type": "stop"}, {"attributes": {"address": null, "at_street": "Fencourt Avenue", "description": null, "latitude": 42.155972, "location_type": 0, "longitude": -71.02939, "municipality": "Randolph", "name": "316 Union St opp Fencourt Ave", "on_street": "Union Street", "platform_code": null, "platform_name": null, "vehicle_type": 3, "wheelchair_boarding": 1}, "id": "4256", "links": {"self": "/stops/4256"}, "relationships": {"facilities": {"links": {"related": "/facilities/?filter[stop]=4256"}}, "parent_station": {"data": null}, "zone": {"data": {"id": "LocalBus", "type": "zone"}}}, "type": "stop"}, {"attributes": {"address": null, "at_street": "Prospect Avenue", "description": null, "latitude": 42.157777, "location_type": 0, "longitude": -71.033183, "municipality": "Randolph", "name": "Union St @ Prospect Ave", "on_street": "Union Street", "platform_code": null, "platform_name": null, "vehicle_type": 3, "wheelchair_boarding": 1}, "id": "4257", "links": {"self": "/stops/4257"}, "relationships": {"facilities": {"links": {"related": "/facilities/?filter[stop]=4257"}}, "parent_station": {"data": null}, "zone": {"data": {"id": "LocalBus", "type": "zone"}}}, "type": "stop"}, {"attributes": {"address": null, "at_street": "South Street", "description": null, "latitude": 42.161855, "location_type": 0, "longitude": -71.040036, "municipality": "Randolph", "name": "Union St @ Howard St", "on_street": "Union Street", "platform_code": null, "platform_name": null, "vehicle_type": 3, "wheelchair_boarding": 1}, "id": "4258", "links": {"self": "/stops/4258"}, "relationships": {"facilities": {"links": {"related": "/facilities/?filter[stop]=4258"}}, "parent_station": {"data": null}, "zone": {"data": {"id": "LocalBus", "type": "zone"}}}, "type": "stop"}, {"attributes": {"address": null, "at_street": "Union Street", "description": null, "latitude": 42.162735, "location_type": 0, "longitude": -71.041184, "municipality": "Randolph", "name": "North St @ Union St", "on_street": "North Street", "platform_code": null, "platform_name": null, "vehicle_type": 3, "wheelchair_boarding": 1}, "id": "4275", "links": {"self": "/stops/4275"}, "relationships": {"facilities": {"links": {"related": "/facilities/?filter[stop]=4275"}}, "parent_station": {"data": null}, "zone": {"data": {"id": "LocalBus", "type": "zone"}}}, "type": "stop"}, {"attributes": {"address": null, "at_street": "Memorial Parkway", "description": null, "latitude": 42.163371, "location_type": 0, "longitude": -71.04184, "municipality": "Randolph", "name": "N Main St opp Memorial Pkwy", "on_street": "North Main Street", "platform_code": null, "platform_name": null, "vehicle_type": 3, "wheelchair_boarding": 1}, "id": "4277", "links": {"self": "/stops/4277"}, "relationships": {"facilities": {"links": {"related": "/facilities/?filter[stop]=4277"}}, "parent_station": {"data": null}, "zone": {"data": {"id": "LocalBus", "type": "zone"}}}, "type": "stop"}, {"attributes": {"address": null, "at_street": "Plain Street", "description": null, "latitude": 42.164866, "location_type": 0, "longitude": -71.039387, "municipality": "Randolph", "name": "81 North St", "on_street": "North Street", "platform_code": null, "platform_name": null, "vehicle_type": 3, "wheelchair_boarding": 1}, "id": "4063", "links": {"self": "/stops/4063"}, "relationships": {"facilities": {"links": {"related": "/facilities/?filter[stop]=4063"}}, "parent_station": {"data": null}, "zone": {"data": {"id": "LocalBus", "type": "zone"}}}, "type": "stop"}, {"attributes": {"address": null, "at_street": "Cottage Street", "description": null, "latitude": 42.165905, "location_type": 0, "longitude": -71.038501, "municipality": "Randolph", "name": "North St @ Mill St", "on_street": "North Street", "platform_code": null, "platform_name": null, "vehicle_type": 3, "wheelchair_boarding": 1}, "id": "4061", "links": {"self": "/stops/4061"}, "relationships": {"facilities": {"links": {"related": "/facilities/?filter[stop]=4061"}}, "parent_station": {"data": null}, "zone": {"data": {"id": "LocalBus", "type": "zone"}}}, "type": "stop"}, {"attributes": {"address": null, "at_street": "Pleasant Street", "description": null, "latitude": 42.168345, "location_type": 0, "longitude": -71.036517, "municipality": "Randolph", "name": "203 North St", "on_street": "North Street", "platform_code": null, "platform_name": null, "vehicle_type": 3, "wheelchair_boarding": 1}, "id": "4064", "links": {"self": "/stops/4064"}, "relationships": {"facilities": {"links": {"related": "/facilities/?filter[stop]=4064"}}, "parent_station": {"data": null}, "zone": {"data": {"id": "LocalBus", "type": "zone"}}}, "type": "stop"}, {"attributes": {"address": null, "at_street": "Seton Way", "description": null, "latitude": 42.169691, "location_type": 0, "longitude": -71.035552, "municipality": "Randolph", "name": "North St @ Seton Way", "on_street": "North Street", "platform_code": null, "platform_name": null, "vehicle_type": 3, "wheelchair_boarding": 1}, "id": "4062", "links": {"self": "/stops/4062"}, "relationships": {"facilities": {"links": {"related": "/facilities/?filter[stop]=4062"}}, "parent_station": {"data": null}, "zone": {"data": {"id": "LocalBus", "type": "zone"}}}, "type": "stop"}, {"attributes": {"address": null, "at_street": "Cochato Park", "description": null, "latitude": 42.17176, "location_type": 0, "longitude": -71.034854, "municipality": "Randolph", "name": "North St @ Cochato Pk", "on_street": "North Street", "platform_code": null, "platform_name": null, "vehicle_type": 3, "wheelchair_boarding": 1}, "id": "4065", "links": {"self": "/stops/4065"}, "relationships": {"facilities": {"links": {"related": "/facilities/?filter[stop]=4065"}}, "parent_station": {"data": null}, "zone": {"data": {"id": "LocalBus", "type": "zone"}}}, "type": "stop"}, {"attributes": {"address": null, "at_street": "Trim Way", "description": null, "latitude": 42.173833, "location_type": 0, "longitude": -71.034876, "municipality": "Randolph", "name": "327 North St", "on_street": "North Street", "platform_code": null, "platform_name": null, "vehicle_type": 3, "wheelchair_boarding": 1}, "id": "4066", "links": {"self": "/stops/4066"}, "relationships": {"facilities": {"links": {"related": "/facilities/?filter[stop]=4066"}}, "parent_station": {"data": null}, "zone": {"data": {"id": "LocalBus", "type": "zone"}}}, "type": "stop"}, {"attributes": {"address": null, "at_street": "Dyer Avenue", "description": null, "latitude": 42.176619, "location_type": 0, "longitude": -71.033384, "municipality": "Randolph", "name": "455 North St opp Dyer Ave", "on_street": "North Street", "platform_code": null, "platform_name": null, "vehicle_type": 3, "wheelchair_boarding": 1}, "id": "4069", "links": {"self": "/stops/4069"}, "relationships": {"facilities": {"links": {"related": "/facilities/?filter[stop]=4069"}}, "parent_station": {"data": null}, "zone": {"data": {"id": "LocalBus", "type": "zone"}}}, "type": "stop"}, {"attributes": {"address": null, "at_street": "McDevitt Road", "description": null, "latitude": 42.178165, "location_type": 0, "longitude": -71.030786, "municipality": "Randolph", "name": "North St @ Teed Dr", "on_street": "North Street", "platform_code": null, "platform_name": null, "vehicle_type": 3, "wheelchair_boarding": 1}, "id": "4071", "links": {"self": "/stops/4071"}, "relationships": {"facilities": {"links": {"related": "/facilities/?filter[stop]=4071"}}, "parent_station": {"data": null}, "zone": {"data": {"id": "LocalBus", "type": "zone"}}}, "type": "stop"}, {"attributes": {"address": null, "at_street": "Canessa Street", "description": null, "latitude": 42.179866, "location_type": 0, "longitude": -71.029401, "municipality": "Randolph", "name": "North St @ Canessa St", "on_street": "North Street", "platform_code": null, "platform_name": null, "vehicle_type": 3, "wheelchair_boarding": 1}, "id": "4072", "links": {"self": "/stops/4072"}, "relationships": {"facilities": {"links": {"related": "/facilities/?filter[stop]=4072"}}, "parent_station": {"data": null}, "zone": {"data": {"id": "LocalBus", "type": "zone"}}}, "type": "stop"}, {"attributes": {"address": null, "at_street": null, "description": null, "latitude": 42.182885, "location_type": 0, "longitude": -71.028109, "municipality": "Randolph", "name": "North St opp Scannel Rd", "on_street": "North Street", "platform_code": null, "platform_name": null, "vehicle_type": 3, "wheelchair_boarding": 1}, "id": "4074", "links": {"self": "/stops/4074"}, "relationships": {"facilities": {"links": {"related": "/facilities/?filter[stop]=4074"}}, "parent_station": {"data": null}, "zone": {"data": {"id": "LocalBus", "type": "zone"}}}, "type": "stop"}, {"attributes": {"address": null, "at_street": "Alward Drive", "description": null, "latitude": 42.187114, "location_type": 0, "longitude": -71.029484, "municipality": "Randolph", "name": "North St @ Randolph Rd", "on_street": "North Street", "platform_code": null, "platform_name": null, "vehicle_type": 3, "wheelchair_boarding": 2}, "id": "4075", "links": {"self": "/stops/4075"}, "relationships": {"facilities": {"links": {"related": "/facilities/?filter[stop]=4075"}}, "parent_station": {"data": null}, "zone": {"data": {"id": "LocalBus", "type": "zone"}}}, "type": "stop"}, {"attributes": {"address": null, "at_street": "Broad Street", "description": null, "latitude": 42.188018, "location_type": 0, "longitude": -71.029746, "municipality": "Randolph", "name": "North St opp Broad St", "on_street": "North Street", "platform_code": null, "platform_name": null, "vehicle_type": 3, "wheelchair_boarding": 1}, "id": "4076", "links": {"self": "/stops/4076"}, "relationships": {"facilities": {"links": {"related": "/facilities/?filter[stop]=4076"}}, "parent_station": {"data": null}, "zone": {"data": {"id": "LocalBus", "type": "zone"}}}, "type": "stop"}, {"attributes": {"address": null, "at_street": null, "description": null, "latitude": 42.1913, "location_type": 0, "longitude": -71.029647, "municipality": "Randolph", "name": "North St opp Maitland Ave", "on_street": "North Street", "platform_code": null, "platform_name": null, "vehicle_type": 3, "wheelchair_boarding": 1}, "id": "4078", "links": {"self": "/stops/4078"}, "relationships": {"facilities": {"links": {"related": "/facilities/?filter[stop]=4078"}}, "parent_station": {"data": null}, "zone": {"data": {"id": "LocalBus", "type": "zone"}}}, "type": "stop"}, {"attributes": {"address": null, "at_street": "Rocsam Park Road", "description": null, "latitude": 42.193706, "location_type": 0, "longitude": -71.028438, "municipality": "Braintree", "name": "Pond St @ Ida Rd", "on_street": "Pond Street", "platform_code": null, "platform_name": null, "vehicle_type": 3, "wheelchair_boarding": 1}, "id": "4079", "links": {"self": "/stops/4079"}, "relationships": {"facilities": {"links": {"related": "/facilities/?filter[stop]=4079"}}, "parent_station": {"data": null}, "zone": {"data": {"id": "LocalBus", "type": "zone"}}}, "type": "stop"}, {"attributes": {"address": null, "at_street": "Margaret Drive", "description": null, "latitude": 42.196568, "location_type": 0, "longitude": -71.027616, "municipality": "Braintree", "name": "Pond St opp Margaret Dr", "on_street": "Pond Street", "platform_code": null, "platform_name": null, "vehicle_type": 3, "wheelchair_boarding": 1}, "id": "4081", "links": {"self": "/stops/4081"}, "relationships": {"facilities": {"links": {"related": "/facilities/?filter[stop]=4081"}}, "parent_station": {"data": null}, "zone": {"data": {"id": "LocalBus", "type": "zone"}}}, "type": "stop"}, {"attributes": {"address": null, "at_street": "King Hill Road", "description": null, "latitude": 42.198972, "location_type": 0, "longitude": -71.025935, "municipality": "Braintree", "name": "Granite St @ Pond St", "on_street": "Granite Street", "platform_code": null, "platform_name": null, "vehicle_type": 3, "wheelchair_boarding": 0}, "id": "4082", "links": {"self": "/stops/4082"}, "relationships": {"facilities": {"links": {"related": "/facilities/?filter[stop]=4082"}}, "parent_station": {"data": null}, "zone": {"data": {"id": "LocalBus", "type": "zone"}}}, "type": "stop"}, {"attributes": {"address": null, "at_street": "Lundquist Drive", "description": null, "latitude": 42.202725, "location_type": 0, "longitude": -71.023968, "municipality": "Braintree", "name": "Granite St @ Emerald Ave", "on_street": "Granite Street", "platform_code": null, "platform_name": null, "vehicle_type": 3, "wheelchair_boarding": 1}, "id": "4083", "links": {"self": "/stops/4083"}, "relationships": {"facilities": {"links": {"related": "/facilities/?filter[stop]=4083"}}, "parent_station": {"data": null}, "zone": {"data": {"id": "LocalBus", "type": "zone"}}}, "type": "stop"}, {"attributes": {"address": null, "at_street": "Town Street", "description": null, "latitude": 42.206368, "location_type": 0, "longitude": -71.022107, "municipality": "Braintree", "name": "Granite St @ Town St", "on_street": "Granite Street", "platform_code": null, "platform_name": null, "vehicle_type": 3, "wheelchair_boarding": 1}, "id": "4084", "links": {"self": "/stops/4084"}, "relationships": {"facilities": {"links": {"related": "/facilities/?filter[stop]=4084"}}, "parent_station": {"data": null}, "zone": {"data": {"id": "LocalBus", "type": "zone"}}}, "type": "stop"}, {"attributes": {"address": null, "at_street": "Andersen Road", "description": null, "latitude": 42.208946, "location_type": 0, "longitude": -71.020729, "municipality": "Braintree", "name": "Granite St @ Andersen Rd", "on_street": "Granite Street", "platform_code": null, "platform_name": null, "vehicle_type": 3, "wheelchair_boarding": 1}, "id": "4085", "links": {"self": "/stops/4085"}, "relationships": {"facilities": {"links": {"related": "/facilities/?filter[stop]=4085"}}, "parent_station": {"data": null}, "zone": {"data": {"id": "LocalBus", "type": "zone"}}}, "type": "stop"}, {"attributes": {"address": null, "at_street": "Peterson Road", "description": null, "latitude": 42.211463, "location_type": 0, "longitude": -71.019635, "municipality": "Braintree", "name": "Granite St opp Peterson Rd", "on_street": "Granite Street", "platform_code": null, "platform_name": null, "vehicle_type": 3, "wheelchair_boarding": 1}, "id": "4086", "links": {"self": "/stops/4086"}, "relationships": {"facilities": {"links": {"related": "/facilities/?filter[stop]=4086"}}, "parent_station": {"data": null}, "zone": {"data": {"id": "LocalBus", "type": "zone"}}}, "type": "stop"}, {"attributes": {"address": null, "at_street": "Ross Way", "description": null, "latitude": 42.213009, "location_type": 0, "longitude": -71.020419, "municipality": "Braintree", "name": "Granite St @ West St", "on_street": "Granite Street", "platform_code": null, "platform_name": null, "vehicle_type": 3, "wheelchair_boarding": 1}, "id": "4017", "links": {"self": "/stops/4017"}, "relationships": {"facilities": {"links": {"related": "/facilities/?filter[stop]=4017"}}, "parent_station": {"data": null}, "zone": {"data": {"id": "LocalBus", "type": "zone"}}}, "type": "stop"}, {"attributes": {"address": null, "at_street": null, "description": null, "latitude": 42.217291, "location_type": 0, "longitude": -71.022573, "municipality": "Braintree", "name": "S Shore Mall Rd @ Travelers Ins.", "on_street": null, "platform_code": null, "platform_name": null, "vehicle_type": 3, "wheelchair_boarding": 1}, "id": "4020", "links": {"self": "/stops/4020"}, "relationships": {"facilities": {"links": {"related": "/facilities/?filter[stop]=4020"}}, "parent_station": {"data": null}, "zone": {"data": {"id": "LocalBus", "type": "zone"}}}, "type": "stop"}, {"attributes": {"address": null, "at_street": null, "description": null, "latitude": 42.220488, "location_type": 0, "longitude": -71.023648, "municipality": "Braintree", "name": "S Shore Plaza @ Garage", "on_street": null, "platform_code": null, "platform_name": null, "vehicle_type": 3, "wheelchair_boarding": 1}, "id": "4019", "links": {"self": "/stops/4019"}, "relationships": {"facilities": {"links": {"related": "/facilities/?filter[stop]=4019"}}, "parent_station": {"data": null}, "zone": {"data": {"id": "LocalBus", "type": "zone"}}}, "type": "stop"}, {"attributes": {"address": null, "at_street": "Rockdale Street", "description": null, "latitude": 42.226198, "location_type": 0, "longitude": -71.031754, "municipality": "Braintree", "name": "Granite St @ Braintree Hill Pk", "on_street": "Granite Street", "platform_code": null, "platform_name": null, "vehicle_type": 3, "wheelchair_boarding": 1}, "id": "4087", "links": {"self": "/stops/4087"}, "relationships": {"facilities": {"links": {"related": "/facilities/?filter[stop]=4087"}}, "parent_station": {"data": null}, "zone": {"data": {"id": "LocalBus", "type": "zone"}}}, "type": "stop"}, {"attributes": {"address": null, "at_street": null, "description": null, "latitude": 42.228625, "location_type": 0, "longitude": -71.031212, "municipality": "Quincy", "name": "Opp 859 Willard St", "on_street": "Willard Street", "platform_code": null, "platform_name": null, "vehicle_type": 3, "wheelchair_boarding": 1}, "id": "4088", "links": {"self": "/stops/4088"}, "relationships": {"facilities": {"links": {"related": "/facilities/?filter[stop]=4088"}}, "parent_station": {"data": null}, "zone": {"data": {"id": "LocalBus", "type": "zone"}}}, "type": "stop"}, {"attributes": {"address": null, "at_street": "Purgatory Road", "description": null, "latitude": 42.22958, "location_type": 0, "longitude": -71.030926, "municipality": "Quincy", "name": "Willard St @ Thistle Rd", "on_street": "Willard Street", "platform_code": null, "platform_name": null, "vehicle_type": 3, "wheelchair_boarding": 1}, "id": "4089", "links": {"self": "/stops/4089"}, "relationships": {"facilities": {"links": {"related": "/facilities/?filter[stop]=4089"}}, "parent_station": {"data": null}, "zone": {"data": {"id": "LocalBus", "type": "zone"}}}, "type": "stop"}, {"attributes": {"address": null, "at_street": "Ames Street", "description": null, "latitude": 42.234611, "location_type": 0, "longitude": -71.0285, "municipality": "Quincy", "name": "Willard St @ Ames St", "on_street": "Willard Street", "platform_code": null, "platform_name": null, "vehicle_type": 3, "wheelchair_boarding": 1}, "id": "4092", "links": {"self": "/stops/4092"}, "relationships": {"facilities": {"links": {"related": "/facilities/?filter[stop]=4092"}}, "parent_station": {"data": null}, "zone": {"data": {"id": "LocalBus", "type": "zone"}}}, "type": "stop"}, {"attributes": {"address": null, "at_street": "Wesson Avenue", "description": null, "latitude": 42.235738, "location_type": 0, "longitude": -71.028307, "municipality": "Quincy", "name": "West St @ Willard St", "on_street": "West Street", "platform_code": null, "platform_name": null, "vehicle_type": 3, "wheelchair_boarding": 1}, "id": "4093", "links": {"self": "/stops/4093"}, "relationships": {"facilities": {"links": {"related": "/facilities/?filter[stop]=4093"}}, "parent_station": {"data": null}, "zone": {"data": {"id": "LocalBus", "type": "zone"}}}, "type": "stop"}, {"attributes": {"address": null, "at_street": "Trask Avenue", "description": null, "latitude": 42.237471, "location_type": 0, "longitude": -71.025834, "municipality": "Quincy", "name": "West St @ Trask Ave", "on_street": "West Street", "platform_code": null, "platform_name": null, "vehicle_type": 3, "wheelchair_boarding": 1}, "id": "4094", "links": {"self": "/stops/4094"}, "relationships": {"facilities": {"links": {"related": "/facilities/?filter[stop]=4094"}}, "parent_station": {"data": null}, "zone": {"data": {"id": "LocalBus", "type": "zone"}}}, "type": "stop"}, {"attributes": {"address": null, "at_street": "Hayden Street", "description": null, "latitude": 42.238421, "location_type": 0, "longitude": -71.025399, "municipality": "Quincy", "name": "West St opp Hayden St", "on_street": "West Street", "platform_code": null, "platform_name": null, "vehicle_type": 3, "wheelchair_boarding": 0}, "id": "4095", "links": {"self": "/stops/4095"}, "relationships": {"facilities": {"links": {"related": "/facilities/?filter[stop]=4095"}}, "parent_station": {"data": null}, "zone": {"data": {"id": "LocalBus", "type": "zone"}}}, "type": "stop"}, {"attributes": {"address": null, "at_street": null, "description": null, "latitude": 42.239658, "location_type": 0, "longitude": -71.024833, "municipality": "Quincy", "name": "West St @ Doble St", "on_street": "West Street", "platform_code": null, "platform_name": null, "vehicle_type": 3, "wheelchair_boarding": 1}, "id": "4096", "links": {"self": "/stops/4096"}, "relationships": {"facilities": {"links": {"related": "/facilities/?filter[stop]=4096"}}, "parent_station": {"data": null}, "zone": {"data": {"id": "LocalBus", "type": "zone"}}}, "type": "stop"}, {"attributes": {"address": null, "at_street": "Ida Street", "description": null, "latitude": 42.240545, "location_type": 0, "longitude": -71.024105, "municipality": "Quincy", "name": "West St @ Sullivan Rd", "on_street": "West Street", "platform_code": null, "platform_name": null, "vehicle_type": 3, "wheelchair_boarding": 0}, "id": "4097", "links": {"self": "/stops/4097"}, "relationships": {"facilities": {"links": {"related": "/facilities/?filter[stop]=4097"}}, "parent_station": {"data": null}, "zone": {"data": {"id": "LocalBus", "type": "zone"}}}, "type": "stop"}, {"attributes": {"address": null, "at_street": "Lyons Street", "description": null, "latitude": 42.241367, "location_type": 0, "longitude": -71.023124, "municipality": "Quincy", "name": "West St @ Hynes Ave", "on_street": "West Street", "platform_code": null, "platform_name": null, "vehicle_type": 3, "wheelchair_boarding": 1}, "id": "4098", "links": {"self": "/stops/4098"}, "relationships": {"facilities": {"links": {"related": "/facilities/?filter[stop]=4098"}}, "parent_station": {"data": null}, "zone": {"data": {"id": "LocalBus", "type": "zone"}}}, "type": "stop"}, {"attributes": {"address": null, "at_street": "Centre Street", "description": null, "latitude": 42.241865, "location_type": 0, "longitude": -71.021417, "municipality": "Quincy", "name": "West St @ Centre St", "on_street": "West Street", "platform_code": null, "platform_name": null, "vehicle_type": 3, "wheelchair_boarding": 1}, "id": "4099", "links": {"self": "/stops/4099"}, "relationships": {"facilities": {"links": {"related": "/facilities/?filter[stop]=4099"}}, "parent_station": {"data": null}, "zone": {"data": {"id": "LocalBus", "type": "zone"}}}, "type": "stop"}, {"attributes": {"address": null, "at_street": "McDonald Street", "description": null, "latitude": 42.24121, "location_type": 0, "longitude": -71.019643, "municipality": "Quincy", "name": "Centre St @ McDonald St", "on_street": "Centre Street", "platform_code": null, "platform_name": null, "vehicle_type": 3, "wheelchair_boarding": 1}, "id": "4100", "links": {"self": "/stops/4100"}, "relationships": {"facilities": {"links": {"related": "/facilities/?filter[stop]=4100"}}, "parent_station": {"data": null}, "zone": {"data": {"id": "LocalBus", "type": "zone"}}}, "type": "stop"}, {"attributes": {"address": null, "at_street": "Brewer Street", "description": null, "latitude": 42.23944, "location_type": 0, "longitude": -71.016616, "municipality": "Quincy", "name": "Centre St @ Bartlett St", "on_street": "Centre Street", "platform_code": null, "platform_name": null, "vehicle_type": 3, "wheelchair_boarding": 1}, "id": "4101", "links": {"self": "/stops/4101"}, "relationships": {"facilities": {"links": {"related": "/facilities/?filter[stop]=4101"}}, "parent_station": {"data": null}, "zone": {"data": {"id": "LocalBus", "type": "zone"}}}, "type": "stop"}, {"attributes": {"address": null, "at_street": "Brooks Avenue", "description": null, "latitude": 42.23795, "location_type": 0, "longitude": -71.015132, "municipality": "Quincy", "name": "Centre St @ Albertina St", "on_street": "Centre Street", "platform_code": null, "platform_name": null, "vehicle_type": 3, "wheelchair_boarding": 1}, "id": "4102", "links": {"self": "/stops/4102"}, "relationships": {"facilities": {"links": {"related": "/facilities/?filter[stop]=4102"}}, "parent_station": {"data": null}, "zone": {"data": {"id": "LocalBus", "type": "zone"}}}, "type": "stop"}, {"attributes": {"address": null, "at_street": "Intervale Street", "description": null, "latitude": 42.23644, "location_type": 0, "longitude": -71.013608, "municipality": "Quincy", "name": "Centre St @ Intervale St", "on_street": "Centre Street", "platform_code": null, "platform_name": null, "vehicle_type": 3, "wheelchair_boarding": 1}, "id": "4103", "links": {"self": "/stops/4103"}, "relationships": {"facilities": {"links": {"related": "/facilities/?filter[stop]=4103"}}, "parent_station": {"data": null}, "zone": {"data": {"id": "LocalBus", "type": "zone"}}}, "type": "stop"}, {"attributes": {"address": null, "at_street": "Liberty Street", "description": null, "latitude": 42.234737, "location_type": 0, "longitude": -71.011882, "municipality": "Quincy", "name": "Centre St @ Liberty St", "on_street": "Centre Street", "platform_code": null, "platform_name": null, "vehicle_type": 3, "wheelchair_boarding": 1}, "id": "41032", "links": {"self": "/stops/41032"}, "relationships": {"facilities": {"links": {"related": "/facilities/?filter[stop]=41032"}}, "parent_station": {"data": null}, "zone": {"data": {"id": "LocalBus", "type": "zone"}}}, "type": "stop"}, {"attributes": {"address": null, "at_street": null, "description": null, "latitude": 42.233844, "location_type": 0, "longitude": -71.010995, "municipality": "Quincy", "name": "Centre St @ Crown Colony Dr", "on_street": "Centre Street", "platform_code": null, "platform_name": null, "vehicle_type": 3, "wheelchair_boarding": 1}, "id": "41033", "links": {"self": "/stops/41033"}, "relationships": {"facilities": {"links": {"related": "/facilities/?filter[stop]=41033"}}, "parent_station": {"data": null}, "zone": {"data": {"id": "LocalBus", "type": "zone"}}}, "type": "stop"}, {"attributes": {"address": null, "at_street": "Centre Street", "description": null, "latitude": 42.228612, "location_type": 0, "longitude": -71.004914, "municipality": "Braintree", "name": "Independence Ave opp Centre St", "on_street": "Independence Avenue", "platform_code": null, "platform_name": null, "vehicle_type": 3, "wheelchair_boarding": 0}, "id": "3943", "links": {"self": "/stops/3943"}, "relationships": {"facilities": {"links": {"related": "/facilities/?filter[stop]=3943"}}, "parent_station": {"data": null}, "zone": {"data": {"id": "LocalBus", "type": "zone"}}}, "type": "stop"}, {"attributes": {"address": null, "at_street": "Holmes Street", "description": null, "latitude": 42.230195, "location_type": 0, "longitude": -71.005259, "municipality": "Braintree", "name": "Opp 41 Independence Ave", "on_street": "Independence Avenue", "platform_code": null, "platform_name": null, "vehicle_type": 3, "wheelchair_boarding": 1}, "id": "3944", "links": {"self": "/stops/3944"}, "relationships": {"facilities": {"links": {"related": "/facilities/?filter[stop]=3944"}}, "parent_station": {"data": null}, "zone": {"data": {"id": "LocalBus", "type": "zone"}}}, "type": "stop"}, {"attributes": {"address": null, "at_street": "Lurton Street", "description": null, "latitude": 42.231897, "location_type": 0, "longitude": -71.005637, "municipality": "Quincy", "name": "Independence Ave @ Lurton St", "on_street": "Independence Avenue", "platform_code": null, "platform_name": null, "vehicle_type": 3, "wheelchair_boarding": 1}, "id": "3945", "links": {"self": "/stops/3945"}, "relationships": {"facilities": {"links": {"related": "/facilities/?filter[stop]=3945"}}, "parent_station": {"data": null}, "zone": {"data": {"id": "LocalBus", "type": "zone"}}}, "type": "stop"}, {"attributes": {"address": null, "at_street": "Verchild Street", "description": null, "latitude": 42.233339, "location_type": 0, "longitude": -71.005958, "municipality": "Quincy", "name": "Independence Ave @ Verchild St", "on_street": "Independence Avenue", "platform_code": null, "platform_name": null, "vehicle_type": 3, "wheelchair_boarding": 1}, "id": "3946", "links": {"self": "/stops/3946"}, "relationships": {"facilities": {"links": {"related": "/facilities/?filter[stop]=3946"}}, "parent_station": {"data": null}, "zone": {"data": {"id": "LocalBus", "type": "zone"}}}, "type": "stop"}, {"attributes": {"address": null, "at_street": "Federal Avenue", "description": null, "latitude": 42.234888, "location_type": 0, "longitude": -71.005705, "municipality": "Quincy", "name": "Independence Ave @ Federal Ave", "on_street": "Independence Avenue", "platform_code": null, "platform_name": null, "vehicle_type": 3, "wheelchair_boarding": 1}, "id": "3947", "links": {"self": "/stops/3947"}, "relationships": {"facilities": {"links": {"related": "/facilities/?filter[stop]=3947"}}, "parent_station": {"data": null}, "zone": {"data": {"id": "LocalBus", "type": "zone"}}}, "type": "stop"}, {"attributes": {"address": null, "at_street": "Bennington Street", "description": null, "latitude": 42.236815, "location_type": 0, "longitude": -71.004535, "municipality": "Quincy", "name": "Independence Ave @ Bennington St", "on_street": "Independence Avenue", "platform_code": null, "platform_name": null, "vehicle_type": 3, "wheelchair_boarding": 0}, "id": "3948", "links": {"self": "/stops/3948"}, "relationships": {"facilities": {"links": {"related": "/facilities/?filter[stop]=3948"}}, "parent_station": {"data": null}, "zone": {"data": {"id": "LocalBus", "type": "zone"}}}, "type": "stop"}, {"attributes": {"address": null, "at_street": "Presidents Avenue", "description": null, "latitude": 42.238625, "location_type": 0, "longitude": -71.00341, "municipality": "Quincy", "name": "Independence Ave @ Franklin St", "on_street": "Independence Avenue", "platform_code": null, "platform_name": null, "vehicle_type": 3, "wheelchair_boarding": 1}, "id": "3949", "links": {"self": "/stops/3949"}, "relationships": {"facilities": {"links": {"related": "/facilities/?filter[stop]=3949"}}, "parent_station": {"data": null}, "zone": {"data": {"id": "LocalBus", "type": "zone"}}}, "type": "stop"}, {"attributes": {"address": null, "at_street": "Payne Street", "description": null, "latitude": 42.239655, "location_type": 0, "longitude": -71.00318, "municipality": "Quincy", "name": "Franklin St @ Payne St", "on_street": "Franklin Street", "platform_code": null, "platform_name": null, "vehicle_type": 3, "wheelchair_boarding": 1}, "id": "3950", "links": {"self": "/stops/3950"}, "relationships": {"facilities": {"links": {"related": "/facilities/?filter[stop]=3950"}}, "parent_station": {"data": null}, "zone": {"data": {"id": "LocalBus", "type": "zone"}}}, "type": "stop"}, {"attributes": {"address": null, "at_street": "Pearl Street", "description": null, "latitude": 42.241031, "location_type": 0, "longitude": -71.003354, "municipality": "Quincy", "name": "Franklin St @ Pearl St", "on_street": "Franklin Street", "platform_code": null, "platform_name": null, "vehicle_type": 3, "wheelchair_boarding": 1}, "id": "3959", "links": {"self": "/stops/3959"}, "relationships": {"facilities": {"links": {"related": "/facilities/?filter[stop]=3959"}}, "parent_station": {"data": null}, "zone": {"data": {"id": "LocalBus", "type": "zone"}}}, "type": "stop"}, {"attributes": {"address": null, "at_street": "Water Street", "description": null, "latitude": 42.242025, "location_type": 0, "longitude": -71.003462, "municipality": "Quincy", "name": "Franklin St @ Water St", "on_street": "Franklin Street", "platform_code": null, "platform_name": null, "vehicle_type": 3, "wheelchair_boarding": 1}, "id": "3418", "links": {"self": "/stops/3418"}, "relationships": {"facilities": {"links": {"related": "/facilities/?filter[stop]=3418"}}, "parent_station": {"data": null}, "zone": {"data": {"id": "LocalBus", "type": "zone"}}}, "type": "stop"}, {"attributes": {"address": null, "at_street": "Phipps Street", "description": null, "latitude": 42.24419, "location_type": 0, "longitude": -71.002731, "municipality": "Quincy", "name": "School St @ Phipps St", "on_street": "School Street", "platform_code": null, "platform_name": null, "vehicle_type": 3, "wheelchair_boarding": 1}, "id": "3420", "links": {"self": "/stops/3420"}, "relationships": {"facilities": {"links": {"related": "/facilities/?filter[stop]=3420"}}, "parent_station": {"data": null}, "zone": {"data": {"id": "LocalBus", "type": "zone"}}}, "type": "stop"}, {"attributes": {"address": null, "at_street": "Revere Road", "description": null, "latitude": 42.246696, "location_type": 0, "longitude": -71.000719, "municipality": "Quincy", "name": "Hancock St @ Walter J Hannon Pkwy", "on_street": "Hancock Street", "platform_code": null, "platform_name": null, "vehicle_type": 3, "wheelchair_boarding": 1}, "id": "3422", "links": {"self": "/stops/3422"}, "relationships": {"facilities": {"links": {"related": "/facilities/?filter[stop]=3422"}}, "parent_station": {"data": null}, "zone": {"data": {"id": "LocalBus", "type": "zone"}}}, "type": "stop"}, {"attributes": {"address": null, "at_street": "Cottage Avenue", "description": null, "latitude": 42.248397, "location_type": 0, "longitude": -71.001703, "municipality": "Quincy", "name": "Hancock St @ Cottage Ave", "on_street": "Hancock Street", "platform_code": null, "platform_name": null, "vehicle_type": 3, "wheelchair_boarding": 1}, "id": "3423", "links": {"self": "/stops/3423"}, "relationships": {"facilities": {"links": {"related": "/facilities/?filter[stop]=3423"}}, "parent_station": {"data": null}, "zone": {"data": {"id": "LocalBus", "type": "zone"}}}, "type": "stop"}, {"attributes": {"address": null, "at_street": "Hancock Street", "description": null, "latitude": 42.249386, "location_type": 0, "longitude": -71.003366, "municipality": "Quincy", "name": "Granite St @ Hancock St", "on_street": "Granite Street", "platform_code": null, "platform_name": null, "vehicle_type": 3, "wheelchair_boarding": 1}, "id": "33241", "links": {"self": "/stops/33241"}, "relationships": {"facilities": {"links": {"related": "/facilities/?filter[stop]=33241"}}, "parent_station": {"data": null}, "zone": {"data": {"id": "LocalBus", "type": "zone"}}}, "type": "stop"}, {"attributes": {"address": null, "at_street": "Saville Street", "description": null, "latitude": 42.252035, "location_type": 0, "longitude": -71.00588, "municipality": "Quincy", "name": "Burgin Pkwy @ Quincy Center Station", "on_street": "Honorable Thomas S Burgin Parkway", "platform_code": null, "platform_name": null, "vehicle_type": 3, "wheelchair_boarding": 1}, "id": "32000", "links": {"self": "/stops/32000"}, "relationships": {"facilities": {"links": {"related": "/facilities/?filter[stop]=32000"}}, "parent_station": {"data": null}, "zone": {"data": {"id": "LocalBus", "type": "zone"}}}, "type": "stop"}, {"attributes": {"address": null, "at_street": "Ross Way", "description": null, "latitude": 42.213067, "location_type": 0, "longitude": -71.020702, "municipality": "Braintree", "name": "Granite St @ West St", "on_street": "Granite Street", "platform_code": null, "platform_name": null, "vehicle_type": 3, "wheelchair_boarding": 1}, "id": "4024", "links": {"self": "/stops/4024"}, "relationships": {"facilities": {"links": {"related": "/facilities/?filter[stop]=4024"}}, "parent_station": {"data": null}, "zone": {"data": {"id": "LocalBus", "type": "zone"}}}, "type": "stop"}, {"attributes": {"address": null, "at_street": null, "description": null, "latitude": 42.210697, "location_type": 0, "longitude": -71.01998, "municipality": "Braintree", "name": "585 Granite St", "on_street": "Granite Street", "platform_code": null, "platform_name": null, "vehicle_type": 3, "wheelchair_boarding": 1}, "id": "4032", "links": {"self": "/stops/4032"}, "relationships": {"facilities": {"links": {"related": "/facilities/?filter[stop]=4032"}}, "parent_station": {"data": null}, "zone": {"data": {"id": "LocalBus", "type": "zone"}}}, "type": "stop"}, {"attributes": {"address": null, "at_street": "Town Street", "description": null, "latitude": 42.206279, "location_type": 0, "longitude": -71.022351, "municipality": "Braintree", "name": "738 Granite St opp Town St", "on_street": "Granite Street", "platform_code": null, "platform_name": null, "vehicle_type": 3, "wheelchair_boarding": 1}, "id": "4034", "links": {"self": "/stops/4034"}, "relationships": {"facilities": {"links": {"related": "/facilities/?filter[stop]=4034"}}, "parent_station": {"data": null}, "zone": {"data": {"id": "LocalBus", "type": "zone"}}}, "type": "stop"}, {"attributes": {"address": null, "at_street": "Emerald Avenue", "description": null, "latitude": 42.202928, "location_type": 0, "longitude": -71.024, "municipality": "Braintree", "name": "Granite St @ Lundquist Dr", "on_street": "Granite Street", "platform_code": null, "platform_name": null, "vehicle_type": 3, "wheelchair_boarding": 1}, "id": "4035", "links": {"self": "/stops/4035"}, "relationships": {"facilities": {"links": {"related": "/facilities/?filter[stop]=4035"}}, "parent_station": {"data": null}, "zone": {"data": {"id": "LocalBus", "type": "zone"}}}, "type": "stop"}, {"attributes": {"address": null, "at_street": "Pond Street", "description": null, "latitude": 42.199179, "location_type": 0, "longitude": -71.025932, "municipality": "Braintree", "name": "Granite St @ King Hill Rd", "on_street": "Granite Street", "platform_code": null, "platform_name": null, "vehicle_type": 3, "wheelchair_boarding": 0}, "id": "4036", "links": {"self": "/stops/4036"}, "relationships": {"facilities": {"links": {"related": "/facilities/?filter[stop]=4036"}}, "parent_station": {"data": null}, "zone": {"data": {"id": "LocalBus", "type": "zone"}}}, "type": "stop"}, {"attributes": {"address": null, "at_street": "Margaret Drive", "description": null, "latitude": 42.196768, "location_type": 0, "longitude": -71.027666, "municipality": "Braintree", "name": "Pond St @ Margaret Dr", "on_street": "Pond Street", "platform_code": null, "platform_name": null, "vehicle_type": 3, "wheelchair_boarding": 1}, "id": "4037", "links": {"self": "/stops/4037"}, "relationships": {"facilities": {"links": {"related": "/facilities/?filter[stop]=4037"}}, "parent_station": {"data": null}, "zone": {"data": {"id": "LocalBus", "type": "zone"}}}, "type": "stop"}, {"attributes": {"address": null, "at_street": "Ida Road", "description": null, "latitude": 42.193948, "location_type": 0, "longitude": -71.028437, "municipality": "Braintree", "name": "Pond St @ Rocsam Park Rd", "on_street": "Pond Street", "platform_code": null, "platform_name": null, "vehicle_type": 3, "wheelchair_boarding": 1}, "id": "4039", "links": {"self": "/stops/4039"}, "relationships": {"facilities": {"links": {"related": "/facilities/?filter[stop]=4039"}}, "parent_station": {"data": null}, "zone": {"data": {"id": "LocalBus", "type": "zone"}}}, "type": "stop"}, {"attributes": {"address": null, "at_street": "Maitland Avenue", "description": null, "latitude": 42.191015, "location_type": 0, "longitude": -71.029853, "municipality": "Randolph", "name": "North St @ Maitland Ave", "on_street": "North Street", "platform_code": null, "platform_name": null, "vehicle_type": 3, "wheelchair_boarding": 1}, "id": "4040", "links": {"self": "/stops/4040"}, "relationships": {"facilities": {"links": {"related": "/facilities/?filter[stop]=4040"}}, "parent_station": {"data": null}, "zone": {"data": {"id": "LocalBus", "type": "zone"}}}, "type": "stop"}, {"attributes": {"address": null, "at_street": "Broad Street", "description": null, "latitude": 42.188177, "location_type": 0, "longitude": -71.029915, "municipality": "Randolph", "name": "North St @ Broad St", "on_street": "North Street", "platform_code": null, "platform_name": null, "vehicle_type": 3, "wheelchair_boarding": 1}, "id": "4042", "links": {"self": "/stops/4042"}, "relationships": {"facilities": {"links": {"related": "/facilities/?filter[stop]=4042"}}, "parent_station": {"data": null}, "zone": {"data": {"id": "LocalBus", "type": "zone"}}}, "type": "stop"}, {"attributes": {"address": null, "at_street": "Oak Street", "description": null, "latitude": 42.186889, "location_type": 0, "longitude": -71.029537, "municipality": "Randolph", "name": "North St @ Oak St", "on_street": "North Street", "platform_code": null, "platform_name": null, "vehicle_type": 3, "wheelchair_boarding": 1}, "id": "4043", "links": {"self": "/stops/4043"}, "relationships": {"facilities": {"links": {"related": "/facilities/?filter[stop]=4043"}}, "parent_station": {"data": null}, "zone": {"data": {"id": "LocalBus", "type": "zone"}}}, "type": "stop"}, {"attributes": {"address": null, "at_street": "Scannell Road", "description": null, "latitude": 42.18316, "location_type": 0, "longitude": -71.028259, "municipality": "Randolph", "name": "North St @ Scannel Rd", "on_street": "North Street", "platform_code": null, "platform_name": null, "vehicle_type": 3, "wheelchair_boarding": 1}, "id": "4044", "links": {"self": "/stops/4044"}, "relationships": {"facilities": {"links": {"related": "/facilities/?filter[stop]=4044"}}, "parent_station": {"data": null}, "zone": {"data": {"id": "LocalBus", "type": "zone"}}}, "type": "stop"}, {"attributes": {"address": null, "at_street": "Pictun Road", "description": null, "latitude": 42.179659, "location_type": 0, "longitude": -71.029679, "municipality": "Randolph", "name": "North St @ Pictun Rd", "on_street": "North Street", "platform_code": null, "platform_name": null, "vehicle_type": 3, "wheelchair_boarding": 1}, "id": "4046", "links": {"self": "/stops/4046"}, "relationships": {"facilities": {"links": {"related": "/facilities/?filter[stop]=4046"}}, "parent_station": {"data": null}, "zone": {"data": {"id": "LocalBus", "type": "zone"}}}, "type": "stop"}, {"attributes": {"address": null, "at_street": "McDevitt Road", "description": null, "latitude": 42.178233, "location_type": 0, "longitude": -71.030944, "municipality": "Randolph", "name": "North St @ McDevitt Rd", "on_street": "North Street", "platform_code": null, "platform_name": null, "vehicle_type": 3, "wheelchair_boarding": 1}, "id": "4047", "links": {"self": "/stops/4047"}, "relationships": {"facilities": {"links": {"related": "/facilities/?filter[stop]=4047"}}, "parent_station": {"data": null}, "zone": {"data": {"id": "LocalBus", "type": "zone"}}}, "type": "stop"}, {"attributes": {"address": null, "at_street": "Dyer Avenue", "description": null, "latitude": 42.176786, "location_type": 0, "longitude": -71.033227, "municipality": "Randolph", "name": "North St @ Dyer Ave", "on_street": "North Street", "platform_code": null, "platform_name": null, "vehicle_type": 3, "wheelchair_boarding": 1}, "id": "4049", "links": {"self": "/stops/4049"}, "relationships": {"facilities": {"links": {"related": "/facilities/?filter[stop]=4049"}}, "parent_station": {"data": null}, "zone": {"data": {"id": "LocalBus", "type": "zone"}}}, "type": "stop"}, {"attributes": {"address": null, "at_street": "Truman Drive", "description": null, "latitude": 42.176095, "location_type": 0, "longitude": -71.034601, "municipality": "Randolph", "name": "North St @ Truman Dr", "on_street": "North Street", "platform_code": null, "platform_name": null, "vehicle_type": 3, "wheelchair_boarding": 1}, "id": "4050", "links": {"self": "/stops/4050"}, "relationships": {"facilities": {"links": {"related": "/facilities/?filter[stop]=4050"}}, "parent_station": {"data": null}, "zone": {"data": {"id": "LocalBus", "type": "zone"}}}, "type": "stop"}, {"attributes": {"address": null, "at_street": null, "description": null, "latitude": 42.175073, "location_type": 0, "longitude": -71.035187, "municipality": "Randolph", "name": "North St @ Liberty St", "on_street": "North Street", "platform_code": null, "platform_name": null, "vehicle_type": 3, "wheelchair_boarding": 1}, "id": "4051", "links": {"self": "/stops/4051"}, "relationships": {"facilities": {"links": {"related": "/facilities/?filter[stop]=4051"}}, "parent_station": {"data": null}, "zone": {"data": {"id": "LocalBus", "type": "zone"}}}, "type": "stop"}, {"attributes": {"address": null, "at_street": null, "description": null, "latitude": 42.172701, "location_type": 0, "longitude": -71.034931, "municipality": "Randolph", "name": "320 North St", "on_street": "North Street", "platform_code": null, "platform_name": null, "vehicle_type": 3, "wheelchair_boarding": 2}, "id": "4053", "links": {"self": "/stops/4053"}, "relationships": {"facilities": {"links": {"related": "/facilities/?filter[stop]=4053"}}, "parent_station": {"data": null}, "zone": {"data": {"id": "LocalBus", "type": "zone"}}}, "type": "stop"}, {"attributes": {"address": null, "at_street": null, "description": null, "latitude": 42.170367, "location_type": 0, "longitude": -71.035376, "municipality": "Randolph", "name": "North St opp Seton Way", "on_street": "North Street", "platform_code": null, "platform_name": null, "vehicle_type": 3, "wheelchair_boarding": 1}, "id": "4054", "links": {"self": "/stops/4054"}, "relationships": {"facilities": {"links": {"related": "/facilities/?filter[stop]=4054"}}, "parent_station": {"data": null}, "zone": {"data": {"id": "LocalBus", "type": "zone"}}}, "type": "stop"}, {"attributes": {"address": null, "at_street": "Pleasant Street", "description": null, "latitude": 42.167941, "location_type": 0, "longitude": -71.03699, "municipality": "Randolph", "name": "168 North St", "on_street": "North Street", "platform_code": null, "platform_name": null, "vehicle_type": 3, "wheelchair_boarding": 1}, "id": "4055", "links": {"self": "/stops/4055"}, "relationships": {"facilities": {"links": {"related": "/facilities/?filter[stop]=4055"}}, "parent_station": {"data": null}, "zone": {"data": {"id": "LocalBus", "type": "zone"}}}, "type": "stop"}, {"attributes": {"address": null, "at_street": "Mill Street", "description": null, "latitude": 42.166217, "location_type": 0, "longitude": -71.03837, "municipality": "Randolph", "name": "North St @ Cottage St", "on_street": "North Street", "platform_code": null, "platform_name": null, "vehicle_type": 3, "wheelchair_boarding": 1}, "id": "4056", "links": {"self": "/stops/4056"}, "relationships": {"facilities": {"links": {"related": "/facilities/?filter[stop]=4056"}}, "parent_station": {"data": null}, "zone": {"data": {"id": "LocalBus", "type": "zone"}}}, "type": "stop"}, {"attributes": {"address": null, "at_street": "Plain Street", "description": null, "latitude": 42.164869, "location_type": 0, "longitude": -71.039538, "municipality": "Randolph", "name": "88 North St", "on_street": "North Street", "platform_code": null, "platform_name": null, "vehicle_type": 3, "wheelchair_boarding": 1}, "id": "14056", "links": {"self": "/stops/14056"}, "relationships": {"facilities": {"links": {"related": "/facilities/?filter[stop]=14056"}}, "parent_station": {"data": null}, "zone": {"data": {"id": "LocalBus", "type": "zone"}}}, "type": "stop"}, {"attributes": {"address": null, "at_street": "Short Street", "description": null, "latitude": 42.164018, "location_type": 0, "longitude": -71.040267, "municipality": "Randolph", "name": "North St @ Short St", "on_street": "North Street", "platform_code": null, "platform_name": null, "vehicle_type": 3, "wheelchair_boarding": 1}, "id": "4057", "links": {"self": "/stops/4057"}, "relationships": {"facilities": {"links": {"related": "/facilities/?filter[stop]=4057"}}, "parent_station": {"data": null}, "zone": {"data": {"id": "LocalBus", "type": "zone"}}}, "type": "stop"}, {"attributes": {"address": null, "at_street": "Union Street", "description": null, "latitude": 42.163067, "location_type": 0, "longitude": -71.041089, "municipality": "Randolph", "name": "North St @ N Main St", "on_street": "North Street", "platform_code": null, "platform_name": null, "vehicle_type": 3, "wheelchair_boarding": 1}, "id": "4058", "links": {"self": "/stops/4058"}, "relationships": {"facilities": {"links": {"related": "/facilities/?filter[stop]=4058"}}, "parent_station": {"data": null}, "zone": {"data": {"id": "LocalBus", "type": "zone"}}}, "type": "stop"}, {"attributes": {"address": null, "at_street": "Howard Street", "description": null, "latitude": 42.161913, "location_type": 0, "longitude": -71.04038, "municipality": "Randolph", "name": "Union St @ South St", "on_street": "Union Street", "platform_code": null, "platform_name": null, "vehicle_type": 3, "wheelchair_boarding": 1}, "id": "4252", "links": {"self": "/stops/4252"}, "relationships": {"facilities": {"links": {"related": "/facilities/?filter[stop]=4252"}}, "parent_station": {"data": null}, "zone": {"data": {"id": "LocalBus", "type": "zone"}}}, "type": "stop"}, {"attributes": {"address": null, "at_street": "Boothby Circle", "description": null, "latitude": 42.15739, "location_type": 0, "longitude": -71.032509, "municipality": "Randolph", "name": "Union St @ Boothby Cir", "on_street": "Union Street", "platform_code": null, "platform_name": null, "vehicle_type": 3, "wheelchair_boarding": 1}, "id": "4253", "links": {"self": "/stops/4253"}, "relationships": {"facilities": {"links": {"related": "/facilities/?filter[stop]=4253"}}, "parent_station": {"data": null}, "zone": {"data": {"id": "LocalBus", "type": "zone"}}}, "type": "stop"}, {"attributes": {"address": null, "at_street": "Fencourt Avenue", "description": null, "latitude": 42.156078, "location_type": 0, "longitude": -71.029729, "municipality": "Randolph", "name": "Union St @ Fencourt Ave", "on_street": "Union Street", "platform_code": null, "platform_name": null, "vehicle_type": 3, "wheelchair_boarding": 1}, "id": "4254", "links": {"self": "/stops/4254"}, "relationships": {"facilities": {"links": {"related": "/facilities/?filter[stop]=4254"}}, "parent_station": {"data": null}, "zone": {"data": {"id": "LocalBus", "type": "zone"}}}, "type": "stop"}, {"attributes": {"address": null, "at_street": "North Main Street", "description": null, "latitude": 42.161567, "location_type": 0, "longitude": -71.041972, "municipality": "Randolph", "name": "Opp 32 S Main St", "on_street": "South Main Street", "platform_code": null, "platform_name": null, "vehicle_type": 3, "wheelchair_boarding": 1}, "id": "4214", "links": {"self": "/stops/4214"}, "relationships": {"facilities": {"links": {"related": "/facilities/?filter[stop]=4214"}}, "parent_station": {"data": null}, "zone": {"data": {"id": "LocalBus", "type": "zone"}}}, "type": "stop"}, {"attributes": {"address": null, "at_street": null, "description": null, "latitude": 42.159481, "location_type": 0, "longitude": -71.043111, "municipality": "Randolph", "name": "S Main St @ Elgin Court", "on_street": "South Main Street", "platform_code": null, "platform_name": null, "vehicle_type": 3, "wheelchair_boarding": 1}, "id": "4215", "links": {"self": "/stops/4215"}, "relationships": {"facilities": {"links": {"related": "/facilities/?filter[stop]=4215"}}, "parent_station": {"data": null}, "zone": {"data": {"id": "LocalBus", "type": "zone"}}}, "type": "stop"}, {"attributes": {"address": null, "at_street": "Van Beal Road", "description": null, "latitude": 42.15862, "location_type": 0, "longitude": -71.0435, "municipality": "Randolph", "name": "S Main St @ Woodlawn St", "on_street": "South Main Street", "platform_code": null, "platform_name": null, "vehicle_type": 3, "wheelchair_boarding": 1}, "id": "4216", "links": {"self": "/stops/4216"}, "relationships": {"facilities": {"links": {"related": "/facilities/?filter[stop]=4216"}}, "parent_station": {"data": null}, "zone": {"data": {"id": "LocalBus", "type": "zone"}}}, "type": "stop"}, {"attributes": {"address": null, "at_street": "Darrell Drive", "description": null, "latitude": 42.15705, "location_type": 0, "longitude": -71.044146, "municipality": "Randolph", "name": "S Main St @ Fairview Ave", "on_street": "South Main Street", "platform_code": null, "platform_name": null, "vehicle_type": 3, "wheelchair_boarding": 1}, "id": "4217", "links": {"self": "/stops/4217"}, "relationships": {"facilities": {"links": {"related": "/facilities/?filter[stop]=4217"}}, "parent_station": {"data": null}, "zone": {"data": {"id": "LocalBus", "type": "zone"}}}, "type": "stop"}, {"attributes": {"address": null, "at_street": "Fairmont Street", "description": null, "latitude": 42.15611, "location_type": 0, "longitude": -71.04454, "municipality": "Randolph", "name": "S Main St @ Fairmount St", "on_street": "South Main Street", "platform_code": null, "platform_name": null, "vehicle_type": 3, "wheelchair_boarding": 1}, "id": "4218", "links": {"self": "/stops/4218"}, "relationships": {"facilities": {"links": {"related": "/facilities/?filter[stop]=4218"}}, "parent_station": {"data": null}, "zone": {"data": {"id": "LocalBus", "type": "zone"}}}, "type": "stop"}, {"attributes": {"address": null, "at_street": "Cole Terrace", "description": null, "latitude": 42.154754, "location_type": 0, "longitude": -71.04504, "municipality": "Randolph", "name": "S Main St @ Cole Terr", "on_street": "South Main Street", "platform_code": null, "platform_name": null, "vehicle_type": 3, "wheelchair_boarding": 1}, "id": "4219", "links": {"self": "/stops/4219"}, "relationships": {"facilities": {"links": {"related": "/facilities/?filter[stop]=4219"}}, "parent_station": {"data": null}, "zone": {"data": {"id": "LocalBus", "type": "zone"}}}, "type": "stop"}, {"attributes": {"address": null, "at_street": "Fitch Terrace", "description": null, "latitude": 42.153196, "location_type": 0, "longitude": -71.045175, "municipality": "Randolph", "name": "S Main St @ Fitch Terr", "on_street": "South Main Street", "platform_code": null, "platform_name": null, "vehicle_type": 3, "wheelchair_boarding": 1}, "id": "4220", "links": {"self": "/stops/4220"}, "relationships": {"facilities": {"links": {"related": "/facilities/?filter[stop]=4220"}}, "parent_station": {"data": null}, "zone": {"data": {"id": "LocalBus", "type": "zone"}}}, "type": "stop"}, {"attributes": {"address": null, "at_street": "Richard Road", "description": null, "latitude": 42.151808, "location_type": 0, "longitude": -71.044611, "municipality": "Randolph", "name": "309 S Main opp Richard Rd", "on_street": "South Main Street", "platform_code": null, "platform_name": null, "vehicle_type": 3, "wheelchair_boarding": 1}, "id": "4221", "links": {"self": "/stops/4221"}, "relationships": {"facilities": {"links": {"related": "/facilities/?filter[stop]=4221"}}, "parent_station": {"data": null}, "zone": {"data": {"id": "LocalBus", "type": "zone"}}}, "type": "stop"}, {"attributes": {"address": null, "at_street": "Woodland Parkway", "description": null, "latitude": 42.150475, "location_type": 0, "longitude": -71.04427, "municipality": "Randolph", "name": "S Main St @ Stoughton St", "on_street": "South Main Street", "platform_code": null, "platform_name": null, "vehicle_type": 3, "wheelchair_boarding": 1}, "id": "4222", "links": {"self": "/stops/4222"}, "relationships": {"facilities": {"links": {"related": "/facilities/?filter[stop]=4222"}}, "parent_station": {"data": null}, "zone": {"data": {"id": "LocalBus", "type": "zone"}}}, "type": "stop"}, {"attributes": {"address": null, "at_street": "Selwyn Road", "description": null, "latitude": 42.147919, "location_type": 0, "longitude": -71.043244, "municipality": "Randolph", "name": "S Main St @ Selwyn Rd", "on_street": "South Main Street", "platform_code": null, "platform_name": null, "vehicle_type": 3, "wheelchair_boarding": 1}, "id": "4223", "links": {"self": "/stops/4223"}, "relationships": {"facilities": {"links": {"related": "/facilities/?filter[stop]=4223"}}, "parent_station": {"data": null}, "zone": {"data": {"id": "LocalBus", "type": "zone"}}}, "type": "stop"}, {"attributes": {"address": null, "at_street": "Centre Street", "description": null, "latitude": 42.145807, "location_type": 0, "longitude": -71.04208, "municipality": "Randolph", "name": "Opp 530 S Main St", "on_street": "South Main Street", "platform_code": null, "platform_name": null, "vehicle_type": 3, "wheelchair_boarding": 1}, "id": "4224", "links": {"self": "/stops/4224"}, "relationships": {"facilities": {"links": {"related": "/facilities/?filter[stop]=4224"}}, "parent_station": {"data": null}, "zone": {"data": {"id": "LocalBus", "type": "zone"}}}, "type": "stop"}, {"attributes": {"address": null, "at_street": "Centre Street", "description": null, "latitude": 42.144623, "location_type": 0, "longitude": -71.041694, "municipality": "Randolph", "name": "S Main St opp Centre St", "on_street": "South Main Street", "platform_code": null, "platform_name": null, "vehicle_type": 3, "wheelchair_boarding": 1}, "id": "4225", "links": {"self": "/stops/4225"}, "relationships": {"facilities": {"links": {"related": "/facilities/?filter[stop]=4225"}}, "parent_station": {"data": null}, "zone": {"data": {"id": "LocalBus", "type": "zone"}}}, "type": "stop"}, {"attributes": {"address": null, "at_street": "Woodlawn Road", "description": null, "latitude": 42.143804, "location_type": 0, "longitude": -71.041416, "municipality": "Randolph", "name": "S Main St opp Woodlawn Rd", "on_street": "South Main Street", "platform_code": null, "platform_name": null, "vehicle_type": 3, "wheelchair_boarding": 1}, "id": "14225", "links": {"self": "/stops/14225"}, "relationships": {"facilities": {"links": {"related": "/facilities/?filter[stop]=14225"}}, "parent_station": {"data": null}, "zone": {"data": {"id": "LocalBus", "type": "zone"}}}, "type": "stop"}, {"attributes": {"address": null, "at_street": "Frederickson Drive", "description": null, "latitude": 42.14215, "location_type": 0, "longitude": -71.040927, "municipality": "Randolph", "name": "625 S Main St opp Frederickson Dr", "on_street": "South Main Street", "platform_code": null, "platform_name": null, "vehicle_type": 3, "wheelchair_boarding": 1}, "id": "4227", "links": {"self": "/stops/4227"}, "relationships": {"facilities": {"links": {"related": "/facilities/?filter[stop]=4227"}}, "parent_station": {"data": null}, "zone": {"data": {"id": "LocalBus", "type": "zone"}}}, "type": "stop"}, {"attributes": {"address": null, "at_street": "Acorn Drive", "description": null, "latitude": 42.138503, "location_type": 0, "longitude": -71.040245, "municipality": "Randolph", "name": "701 S Main St", "on_street": "South Main Street", "platform_code": null, "platform_name": null, "vehicle_type": 3, "wheelchair_boarding": 1}, "id": "4228", "links": {"self": "/stops/4228"}, "relationships": {"facilities": {"links": {"related": "/facilities/?filter[stop]=4228"}}, "parent_station": {"data": null}, "zone": {"data": {"id": "LocalBus", "type": "zone"}}}, "type": "stop"}, {"attributes": {"address": null, "at_street": "North Main Street", "description": null, "latitude": 42.137248, "location_type": 0, "longitude": -71.040192, "municipality": "Randolph", "name": "N Main St @ Langley Rd", "on_street": "South Main Street", "platform_code": null, "platform_name": null, "vehicle_type": 3, "wheelchair_boarding": 1}, "id": "4229", "links": {"self": "/stops/4229"}, "relationships": {"facilities": {"links": {"related": "/facilities/?filter[stop]=4229"}}, "parent_station": {"data": null}, "zone": {"data": {"id": "LocalBus", "type": "zone"}}}, "type": "stop"}, {"attributes": {"address": null, "at_street": null, "description": null, "latitude": 42.133687, "location_type": 0, "longitude": -71.039778, "municipality": "Avon", "name": "Main St opp Demarco Park", "on_street": "North Main Street", "platform_code": null, "platform_name": null, "vehicle_type": 3, "wheelchair_boarding": 1}, "id": "4230", "links": {"self": "/stops/4230"}, "relationships": {"facilities": {"links": {"related": "/facilities/?filter[stop]=4230"}}, "parent_station": {"data": null}, "zone": {"data": {"id": "LocalBus", "type": "zone"}}}, "type": "stop"}, {"attributes": {"address": null, "at_street": "West Main Street", "description": null, "latitude": 42.131584, "location_type": 0, "longitude": -71.040198, "municipality": "Avon", "name": "E Main St @ W Main St", "on_street": "East Main Street", "platform_code": null, "platform_name": null, "vehicle_type": 3, "wheelchair_boarding": 1}, "id": "4232", "links": {"self": "/stops/4232"}, "relationships": {"facilities": {"links": {"related": "/facilities/?filter[stop]=4232"}}, "parent_station": {"data": null}, "zone": {"data": {"id": "LocalBus", "type": "zone"}}}, "type": "stop"}], "jsonapi": {"version": "1.0"}}